04_librelane_digital/soluzioni/lab01/esempi/semaforo/src/semaforo.vhd
library IEEE;
use IEEE.STD_LOGIC_1164.ALL;

-- =============================================================================
-- Semaforo -- FSM Moore a 3 stati (senza contatore)
-- =============================================================================
-- Ogni stato dura esattamente 1 ciclo di clock.
-- La transizione avviene ad ogni fronte di salita del clock.
-- Design intenzionalmente semplice per mostrare make rtl / make fsm.
--
-- Nota ASIC: nessuna inizializzazione sui segnali.
-- Lo stato iniziale e' imposto esclusivamente dal reset asincrono (rst_n).
-- =============================================================================

entity semaforo is
    port (
        clk    : in  std_logic;
        rst_n  : in  std_logic;
        rosso  : out std_logic;
        verde  : out std_logic;
        giallo : out std_logic
    );
end entity semaforo;

architecture rtl of semaforo is

    type state_t is (ST_ROSSO, ST_VERDE, ST_GIALLO);
    signal state : state_t;

begin

    process(clk, rst_n)
    begin
        if rst_n = '0' then
            state <= ST_ROSSO;
        elsif rising_edge(clk) then
            case state is
                when ST_ROSSO  => state <= ST_VERDE;
                when ST_VERDE  => state <= ST_GIALLO;
                when ST_GIALLO => state <= ST_ROSSO;
                when others    => state <= ST_ROSSO;
            end case;
        end if;
    end process;

    -- Uscite Moore: dipendono solo dallo stato
    rosso  <= '1' when state = ST_ROSSO  else '0';
    verde  <= '1' when state = ST_VERDE  else '0';
    giallo <= '1' when state = ST_GIALLO else '0';

end architecture rtl;

04_librelane_digital/soluzioni/lab01/esempi/semaforo/src/semaforo_tb.vhd
library IEEE;
use IEEE.STD_LOGIC_1164.ALL;

entity semaforo_tb is
end entity semaforo_tb;

architecture sim of semaforo_tb is

    constant CLK_PERIOD : time := 10 ns;

    signal clk    : std_logic := '0';
    signal rst_n  : std_logic := '0';
    signal rosso  : std_logic;
    signal verde  : std_logic;
    signal giallo : std_logic;

begin

    DUT: entity work.semaforo
        port map (
            clk    => clk,
            rst_n  => rst_n,
            rosso  => rosso,
            verde  => verde,
            giallo => giallo
        );

    clk <= not clk after CLK_PERIOD / 2;

    stimoli: process
    begin
        rst_n <= '0';
        wait for CLK_PERIOD * 3;
        rst_n <= '1';
        -- 3 cicli completi: ROSSO->VERDE->GIALLO->ROSSO->...
        wait for CLK_PERIOD * 10;
        report "Simulazione completata." severity NOTE;
        wait;
    end process;

end architecture sim;

04_librelane_digital/soluzioni/lab01/esempi/semaforo/sim/dump.vcd
$date
  Mon May 11 11:15:08 2026
$end
$version
  GHDL v0
$end
$timescale
  1 fs
$end
$scope module standard $end
$upscope $end
$scope module textio $end
$upscope $end
$scope module std_logic_1164 $end
$upscope $end
$scope module semaforo_tb $end
$var reg 1 ! clk $end
$var reg 1 " rst_n $end
$var reg 1 # rosso $end
$var reg 1 $ verde $end
$var reg 1 % giallo $end
$scope module dut $end
$var reg 1 & clk $end
$var reg 1 ' rst_n $end
$var reg 1 ( rosso $end
$var reg 1 ) verde $end
$var reg 1 * giallo $end
$comment state is not handled $end
$upscope $end
$upscope $end
$enddefinitions $end
#0
0!
0"
1#
0$
0%
0&
0'
1(
0)
0*
#5000000
1!
1&
#10000000
0!
0&
#15000000
1!
1&
#20000000
0!
0&
#25000000
1!
1&
#30000000
0!
1"
0&
1'
#35000000
1!
0#
1$
1&
0(
1)
#40000000
0!
0&
#45000000
1!
0$
1%
1&
0)
1*
#50000000
0!
0&
#55000000
1!
1#
0%
1&
1(
0*
#60000000
0!
0&
#65000000
1!
0#
1$
1&
0(
1)
#70000000
0!
0&
#75000000
1!
0$
1%
1&
0)
1*
#80000000
0!
0&
#85000000
1!
1#
0%
1&
1(
0*
#90000000
0!
0&
#95000000
1!
0#
1$
1&
0(
1)
#100000000
0!
0&
#105000000
1!
0$
1%
1&
0)
1*
#110000000
0!
0&
#115000000
1!
1#
0%
1&
1(
0*
#120000000
0!
0&
#125000000
1!
0#
1$
1&
0(
1)
#130000000
0!
0&
#135000000
1!
0$
1%
1&
0)
1*
#140000000
0!
0&
#145000000
1!
1#
0%
1&
1(
0*
#150000000
0!
0&
#155000000
1!
0#
1$
1&
0(
1)
#160000000
0!
0&
#165000000
1!
0$
1%
1&
0)
1*
#170000000
0!
0&
#175000000
1!
1#
0%
1&
1(
0*
#180000000
0!
0&
#185000000
1!
0#
1$
1&
0(
1)
#190000000
0!
0&
#195000000
1!
0$
1%
1&
0)
1*
#200000000
0!
0&
#205000000
1!
1#
0%
1&
1(
0*
#210000000
0!
0&
#215000000
1!
0#
1$
1&
0(
1)
#220000000
0!
0&
#225000000
1!
0$
1%
1&
0)
1*
#230000000
0!
0&
#235000000
1!
1#
0%
1&
1(
0*
#240000000
0!
0&
#245000000
1!
0#
1$
1&
0(
1)
#250000000
0!
0&
#255000000
1!
0$
1%
1&
0)
1*
#260000000
0!
0&
#265000000
1!
1#
0%
1&
1(
0*
#270000000
0!
0&
#275000000
1!
0#
1$
1&
0(
1)
#280000000
0!
0&
#285000000
1!
0$
1%
1&
0)
1*
#290000000
0!
0&
#295000000
1!
1#
0%
1&
1(
0*
#300000000
0!
0&
#305000000
1!
0#
1$
1&
0(
1)
#310000000
0!
0&
#315000000
1!
0$
1%
1&
0)
1*
#320000000
0!
0&
#325000000
1!
1#
0%
1&
1(
0*
#330000000
0!
0&
#335000000
1!
0#
1$
1&
0(
1)
#340000000
0!
0&
#345000000
1!
0$
1%
1&
0)
1*
#350000000
0!
0&
#355000000
1!
1#
0%
1&
1(
0*
#360000000
0!
0&
#365000000
1!
0#
1$
1&
0(
1)
#370000000
0!
0&
#375000000
1!
0$
1%
1&
0)
1*
#380000000
0!
0&
#385000000
1!
1#
0%
1&
1(
0*
#390000000
0!
0&
#395000000
1!
0#
1$
1&
0(
1)
#400000000
0!
0&
#405000000
1!
0$
1%
1&
0)
1*
#410000000
0!
0&
#415000000
1!
1#
0%
1&
1(
0*
#420000000
0!
0&
#425000000
1!
0#
1$
1&
0(
1)
#430000000
0!
0&
#435000000
1!
0$
1%
1&
0)
1*
#440000000
0!
0&
#445000000
1!
1#
0%
1&
1(
0*
#450000000
0!
0&
#455000000
1!
0#
1$
1&
0(
1)
#460000000
0!
0&
#465000000
1!
0$
1%
1&
0)
1*
#470000000
0!
0&
#475000000
1!
1#
0%
1&
1(
0*
#480000000
0!
0&
#485000000
1!
0#
1$
1&
0(
1)
#490000000
0!
0&
#495000000
1!
0$
1%
1&
0)
1*
#500000000
0!
0&
#505000000
1!
1#
0%
1&
1(
0*
#510000000
0!
0&
#515000000
1!
0#
1$
1&
0(
1)
#520000000
0!
0&
#525000000
1!
0$
1%
1&
0)
1*
#530000000
0!
0&
#535000000
1!
1#
0%
1&
1(
0*
#540000000
0!
0&
#545000000
1!
0#
1$
1&
0(
1)
#550000000
0!
0&
#555000000
1!
0$
1%
1&
0)
1*
#560000000
0!
0&
#565000000
1!
1#
0%
1&
1(
0*
#570000000
0!
0&
#575000000
1!
0#
1$
1&
0(
1)
#580000000
0!
0&
#585000000
1!
0$
1%
1&
0)
1*
#590000000
0!
0&
#595000000
1!
1#
0%
1&
1(
0*
#600000000
0!
0&
#605000000
1!
0#
1$
1&
0(
1)
#610000000
0!
0&
#615000000
1!
0$
1%
1&
0)
1*
#620000000
0!
0&
#625000000
1!
1#
0%
1&
1(
0*
#630000000
0!
0&
#635000000
1!
0#
1$
1&
0(
1)
#640000000
0!
0&
#645000000
1!
0$
1%
1&
0)
1*
#650000000
0!
0&
#655000000
1!
1#
0%
1&
1(
0*
#660000000
0!
0&
#665000000
1!
0#
1$
1&
0(
1)
#670000000
0!
0&
#675000000
1!
0$
1%
1&
0)
1*
#680000000
0!
0&
#685000000
1!
1#
0%
1&
1(
0*
#690000000
0!
0&
#695000000
1!
0#
1$
1&
0(
1)
#700000000
0!
0&
#705000000
1!
0$
1%
1&
0)
1*
#710000000
0!
0&
#715000000
1!
1#
0%
1&
1(
0*
#720000000
0!
0&
#725000000
1!
0#
1$
1&
0(
1)
#730000000
0!
0&
#735000000
1!
0$
1%
1&
0)
1*
#740000000
0!
0&
#745000000
1!
1#
0%
1&
1(
0*
#750000000
0!
0&
#755000000
1!
0#
1$
1&
0(
1)
#760000000
0!
0&
#765000000
1!
0$
1%
1&
0)
1*
#770000000
0!
0&
#775000000
1!
1#
0%
1&
1(
0*
#780000000
0!
0&
#785000000
1!
0#
1$
1&
0(
1)
#790000000
0!
0&
#795000000
1!
0$
1%
1&
0)
1*
#800000000
0!
0&
#805000000
1!
1#
0%
1&
1(
0*
#810000000
0!
0&
#815000000
1!
0#
1$
1&
0(
1)
#820000000
0!
0&
#825000000
1!
0$
1%
1&
0)
1*
#830000000
0!
0&
#835000000
1!
1#
0%
1&
1(
0*
#840000000
0!
0&
#845000000
1!
0#
1$
1&
0(
1)
#850000000
0!
0&
#855000000
1!
0$
1%
1&
0)
1*
#860000000
0!
0&
#865000000
1!
1#
0%
1&
1(
0*
#870000000
0!
0&
#875000000
1!
0#
1$
1&
0(
1)
#880000000
0!
0&
#885000000
1!
0$
1%
1&
0)
1*
#890000000
0!
0&
#895000000
1!
1#
0%
1&
1(
0*
#900000000
0!
0&
#905000000
1!
0#
1$
1&
0(
1)
#910000000
0!
0&
#915000000
1!
0$
1%
1&
0)
1*
#920000000
0!
0&
#925000000
1!
1#
0%
1&
1(
0*
#930000000
0!
0&
#935000000
1!
0#
1$
1&
0(
1)
#940000000
0!
0&
#945000000
1!
0$
1%
1&
0)
1*
#950000000
0!
0&
#955000000
1!
1#
0%
1&
1(
0*
#960000000
0!
0&
#965000000
1!
0#
1$
1&
0(
1)
#970000000
0!
0&
#975000000
1!
0$
1%
1&
0)
1*
#980000000
0!
0&
#985000000
1!
1#
0%
1&
1(
0*
#990000000
0!
0&
#995000000
1!
0#
1$
1&
0(
1)
#1000000000
0!
0&
#1005000000
1!
0$
1%
1&
0)
1*
#1010000000
0!
0&
#1015000000
1!
1#
0%
1&
1(
0*
#1020000000
0!
0&
#1025000000
1!
0#
1$
1&
0(
1)
#1030000000
0!
0&
#1035000000
1!
0$
1%
1&
0)
1*
#1040000000
0!
0&
#1045000000
1!
1#
0%
1&
1(
0*
#1050000000
0!
0&
#1055000000
1!
0#
1$
1&
0(
1)
#1060000000
0!
0&
#1065000000
1!
0$
1%
1&
0)
1*
#1070000000
0!
0&
#1075000000
1!
1#
0%
1&
1(
0*
#1080000000
0!
0&
#1085000000
1!
0#
1$
1&
0(
1)
#1090000000
0!
0&
#1095000000
1!
0$
1%
1&
0)
1*
#1100000000
0!
0&
#1105000000
1!
1#
0%
1&
1(
0*
#1110000000
0!
0&
#1115000000
1!
0#
1$
1&
0(
1)
#1120000000
0!
0&
#1125000000
1!
0$
1%
1&
0)
1*
#1130000000
0!
0&
#1135000000
1!
1#
0%
1&
1(
0*
#1140000000
0!
0&
#1145000000
1!
0#
1$
1&
0(
1)
#1150000000
0!
0&
#1155000000
1!
0$
1%
1&
0)
1*
#1160000000
0!
0&
#1165000000
1!
1#
0%
1&
1(
0*
#1170000000
0!
0&
#1175000000
1!
0#
1$
1&
0(
1)
#1180000000
0!
0&
#1185000000
1!
0$
1%
1&
0)
1*
#1190000000
0!
0&
#1195000000
1!
1#
0%
1&
1(
0*
#1200000000
0!
0&
#1205000000
1!
0#
1$
1&
0(
1)
#1210000000
0!
0&
#1215000000
1!
0$
1%
1&
0)
1*
#1220000000
0!
0&
#1225000000
1!
1#
0%
1&
1(
0*
#1230000000
0!
0&
#1235000000
1!
0#
1$
1&
0(
1)
#1240000000
0!
0&
#1245000000
1!
0$
1%
1&
0)
1*
#1250000000
0!
0&
#1255000000
1!
1#
0%
1&
1(
0*
#1260000000
0!
0&
#1265000000
1!
0#
1$
1&
0(
1)
#1270000000
0!
0&
#1275000000
1!
0$
1%
1&
0)
1*
#1280000000
0!
0&
#1285000000
1!
1#
0%
1&
1(
0*
#1290000000
0!
0&
#1295000000
1!
0#
1$
1&
0(
1)
#1300000000
0!
0&
#1305000000
1!
0$
1%
1&
0)
1*
#1310000000
0!
0&
#1315000000
1!
1#
0%
1&
1(
0*
#1320000000
0!
0&
#1325000000
1!
0#
1$
1&
0(
1)
#1330000000
0!
0&
#1335000000
1!
0$
1%
1&
0)
1*
#1340000000
0!
0&
#1345000000
1!
1#
0%
1&
1(
0*
#1350000000
0!
0&
#1355000000
1!
0#
1$
1&
0(
1)
#1360000000
0!
0&
#1365000000
1!
0$
1%
1&
0)
1*
#1370000000
0!
0&
#1375000000
1!
1#
0%
1&
1(
0*
#1380000000
0!
0&
#1385000000
1!
0#
1$
1&
0(
1)
#1390000000
0!
0&
#1395000000
1!
0$
1%
1&
0)
1*
#1400000000
0!
0&
#1405000000
1!
1#
0%
1&
1(
0*
#1410000000
0!
0&
#1415000000
1!
0#
1$
1&
0(
1)
#1420000000
0!
0&
#1425000000
1!
0$
1%
1&
0)
1*
#1430000000
0!
0&
#1435000000
1!
1#
0%
1&
1(
0*
#1440000000
0!
0&
#1445000000
1!
0#
1$
1&
0(
1)
#1450000000
0!
0&
#1455000000
1!
0$
1%
1&
0)
1*
#1460000000
0!
0&
#1465000000
1!
1#
0%
1&
1(
0*
#1470000000
0!
0&
#1475000000
1!
0#
1$
1&
0(
1)
#1480000000
0!
0&
#1485000000
1!
0$
1%
1&
0)
1*
#1490000000
0!
0&
#1495000000
1!
1#
0%
1&
1(
0*
#1500000000
0!
0&
#1505000000
1!
0#
1$
1&
0(
1)
#1510000000
0!
0&
#1515000000
1!
0$
1%
1&
0)
1*
#1520000000
0!
0&
#1525000000
1!
1#
0%
1&
1(
0*
#1530000000
0!
0&
#1535000000
1!
0#
1$
1&
0(
1)
#1540000000
0!
0&
#1545000000
1!
0$
1%
1&
0)
1*
#1550000000
0!
0&
#1555000000
1!
1#
0%
1&
1(
0*
#1560000000
0!
0&
#1565000000
1!
0#
1$
1&
0(
1)
#1570000000
0!
0&
#1575000000
1!
0$
1%
1&
0)
1*
#1580000000
0!
0&
#1585000000
1!
1#
0%
1&
1(
0*
#1590000000
0!
0&
#1595000000
1!
0#
1$
1&
0(
1)
#1600000000
0!
0&
#1605000000
1!
0$
1%
1&
0)
1*
#1610000000
0!
0&
#1615000000
1!
1#
0%
1&
1(
0*
#1620000000
0!
0&
#1625000000
1!
0#
1$
1&
0(
1)
#1630000000
0!
0&
#1635000000
1!
0$
1%
1&
0)
1*
#1640000000
0!
0&
#1645000000
1!
1#
0%
1&
1(
0*
#1650000000
0!
0&
#1655000000
1!
0#
1$
1&
0(
1)
#1660000000
0!
0&
#1665000000
1!
0$
1%
1&
0)
1*
#1670000000
0!
0&
#1675000000
1!
1#
0%
1&
1(
0*
#1680000000
0!
0&
#1685000000
1!
0#
1$
1&
0(
1)
#1690000000
0!
0&
#1695000000
1!
0$
1%
1&
0)
1*
#1700000000
0!
0&
#1705000000
1!
1#
0%
1&
1(
0*
#1710000000
0!
0&
#1715000000
1!
0#
1$
1&
0(
1)
#1720000000
0!
0&
#1725000000
1!
0$
1%
1&
0)
1*
#1730000000
0!
0&
#1735000000
1!
1#
0%
1&
1(
0*
#1740000000
0!
0&
#1745000000
1!
0#
1$
1&
0(
1)
#1750000000
0!
0&
#1755000000
1!
0$
1%
1&
0)
1*
#1760000000
0!
0&
#1765000000
1!
1#
0%
1&
1(
0*
#1770000000
0!
0&
#1775000000
1!
0#
1$
1&
0(
1)
#1780000000
0!
0&
#1785000000
1!
0$
1%
1&
0)
1*
#1790000000
0!
0&
#1795000000
1!
1#
0%
1&
1(
0*
#1800000000
0!
0&
#1805000000
1!
0#
1$
1&
0(
1)
#1810000000
0!
0&
#1815000000
1!
0$
1%
1&
0)
1*
#1820000000
0!
0&
#1825000000
1!
1#
0%
1&
1(
0*
#1830000000
0!
0&
#1835000000
1!
0#
1$
1&
0(
1)
#1840000000
0!
0&
#1845000000
1!
0$
1%
1&
0)
1*
#1850000000
0!
0&
#1855000000
1!
1#
0%
1&
1(
0*
#1860000000
0!
0&
#1865000000
1!
0#
1$
1&
0(
1)
#1870000000
0!
0&
#1875000000
1!
0$
1%
1&
0)
1*
#1880000000
0!
0&
#1885000000
1!
1#
0%
1&
1(
0*
#1890000000
0!
0&
#1895000000
1!
0#
1$
1&
0(
1)
#1900000000
0!
0&
#1905000000
1!
0$
1%
1&
0)
1*
#1910000000
0!
0&
#1915000000
1!
1#
0%
1&
1(
0*
#1920000000
0!
0&
#1925000000
1!
0#
1$
1&
0(
1)
#1930000000
0!
0&
#1935000000
1!
0$
1%
1&
0)
1*
#1940000000
0!
0&
#1945000000
1!
1#
0%
1&
1(
0*
#1950000000
0!
0&
#1955000000
1!
0#
1$
1&
0(
1)
#1960000000
0!
0&
#1965000000
1!
0$
1%
1&
0)
1*
#1970000000
0!
0&
#1975000000
1!
1#
0%
1&
1(
0*
#1980000000
0!
0&
#1985000000
1!
0#
1$
1&
0(
1)
#1990000000
0!
0&
#1995000000
1!
0$
1%
1&
0)
1*
#2000000000
0!
0&
#2005000000
1!
1#
0%
1&
1(
0*
#2010000000
0!
0&
#2015000000
1!
0#
1$
1&
0(
1)
#2020000000
0!
0&
#2025000000
1!
0$
1%
1&
0)
1*
#2030000000
0!
0&
#2035000000
1!
1#
0%
1&
1(
0*
#2040000000
0!
0&
#2045000000
1!
0#
1$
1&
0(
1)
#2050000000
0!
0&
#2055000000
1!
0$
1%
1&
0)
1*
#2060000000
0!
0&
#2065000000
1!
1#
0%
1&
1(
0*
#2070000000
0!
0&
#2075000000
1!
0#
1$
1&
0(
1)
#2080000000
0!
0&
#2085000000
1!
0$
1%
1&
0)
1*
#2090000000
0!
0&
#2095000000
1!
1#
0%
1&
1(
0*
#2100000000
0!
0&
#2105000000
1!
0#
1$
1&
0(
1)
#2110000000
0!
0&
#2115000000
1!
0$
1%
1&
0)
1*
#2120000000
0!
0&
#2125000000
1!
1#
0%
1&
1(
0*
#2130000000
0!
0&
#2135000000
1!
0#
1$
1&
0(
1)
#2140000000
0!
0&
#2145000000
1!
0$
1%
1&
0)
1*
#2150000000
0!
0&
#2155000000
1!
1#
0%
1&
1(
0*
#2160000000
0!
0&
#2165000000
1!
0#
1$
1&
0(
1)
#2170000000
0!
0&
#2175000000
1!
0$
1%
1&
0)
1*
#2180000000
0!
0&
#2185000000
1!
1#
0%
1&
1(
0*
#2190000000
0!
0&
#2195000000
1!
0#
1$
1&
0(
1)
#2200000000
0!
0&
#2205000000
1!
0$
1%
1&
0)
1*
#2210000000
0!
0&
#2215000000
1!
1#
0%
1&
1(
0*
#2220000000
0!
0&
#2225000000
1!
0#
1$
1&
0(
1)
#2230000000
0!
0&
#2235000000
1!
0$
1%
1&
0)
1*
#2240000000
0!
0&
#2245000000
1!
1#
0%
1&
1(
0*
#2250000000
0!
0&
#2255000000
1!
0#
1$
1&
0(
1)
#2260000000
0!
0&
#2265000000
1!
0$
1%
1&
0)
1*
#2270000000
0!
0&
#2275000000
1!
1#
0%
1&
1(
0*
#2280000000
0!
0&
#2285000000
1!
0#
1$
1&
0(
1)
#2290000000
0!
0&
#2295000000
1!
0$
1%
1&
0)
1*
#2300000000
0!
0&
#2305000000
1!
1#
0%
1&
1(
0*
#2310000000
0!
0&
#2315000000
1!
0#
1$
1&
0(
1)
#2320000000
0!
0&
#2325000000
1!
0$
1%
1&
0)
1*
#2330000000
0!
0&
#2335000000
1!
1#
0%
1&
1(
0*
#2340000000
0!
0&
#2345000000
1!
0#
1$
1&
0(
1)
#2350000000
0!
0&
#2355000000
1!
0$
1%
1&
0)
1*
#2360000000
0!
0&
#2365000000
1!
1#
0%
1&
1(
0*
#2370000000
0!
0&
#2375000000
1!
0#
1$
1&
0(
1)
#2380000000
0!
0&
#2385000000
1!
0$
1%
1&
0)
1*
#2390000000
0!
0&
#2395000000
1!
1#
0%
1&
1(
0*
#2400000000
0!
0&
#2405000000
1!
0#
1$
1&
0(
1)
#2410000000
0!
0&
#2415000000
1!
0$
1%
1&
0)
1*
#2420000000
0!
0&
#2425000000
1!
1#
0%
1&
1(
0*
#2430000000
0!
0&
#2435000000
1!
0#
1$
1&
0(
1)
#2440000000
0!
0&
#2445000000
1!
0$
1%
1&
0)
1*
#2450000000
0!
0&
#2455000000
1!
1#
0%
1&
1(
0*
#2460000000
0!
0&
#2465000000
1!
0#
1$
1&
0(
1)
#2470000000
0!
0&
#2475000000
1!
0$
1%
1&
0)
1*
#2480000000
0!
0&
#2485000000
1!
1#
0%
1&
1(
0*
#2490000000
0!
0&
#2495000000
1!
0#
1$
1&
0(
1)
#2500000000
0!
0&
#2505000000
1!
0$
1%
1&
0)
1*
#2510000000
0!
0&
#2515000000
1!
1#
0%
1&
1(
0*
#2520000000
0!
0&
#2525000000
1!
0#
1$
1&
0(
1)
#2530000000
0!
0&
#2535000000
1!
0$
1%
1&
0)
1*
#2540000000
0!
0&
#2545000000
1!
1#
0%
1&
1(
0*
#2550000000
0!
0&
#2555000000
1!
0#
1$
1&
0(
1)
#2560000000
0!
0&
#2565000000
1!
0$
1%
1&
0)
1*
#2570000000
0!
0&
#2575000000
1!
1#
0%
1&
1(
0*
#2580000000
0!
0&
#2585000000
1!
0#
1$
1&
0(
1)
#2590000000
0!
0&
#2595000000
1!
0$
1%
1&
0)
1*
#2600000000
0!
0&
#2605000000
1!
1#
0%
1&
1(
0*
#2610000000
0!
0&
#2615000000
1!
0#
1$
1&
0(
1)
#2620000000
0!
0&
#2625000000
1!
0$
1%
1&
0)
1*
#2630000000
0!
0&
#2635000000
1!
1#
0%
1&
1(
0*
#2640000000
0!
0&
#2645000000
1!
0#
1$
1&
0(
1)
#2650000000
0!
0&
#2655000000
1!
0$
1%
1&
0)
1*
#2660000000
0!
0&
#2665000000
1!
1#
0%
1&
1(
0*
#2670000000
0!
0&
#2675000000
1!
0#
1$
1&
0(
1)
#2680000000
0!
0&
#2685000000
1!
0$
1%
1&
0)
1*
#2690000000
0!
0&
#2695000000
1!
1#
0%
1&
1(
0*
#2700000000
0!
0&
#2705000000
1!
0#
1$
1&
0(
1)
#2710000000
0!
0&
#2715000000
1!
0$
1%
1&
0)
1*
#2720000000
0!
0&
#2725000000
1!
1#
0%
1&
1(
0*
#2730000000
0!
0&
#2735000000
1!
0#
1$
1&
0(
1)
#2740000000
0!
0&
#2745000000
1!
0$
1%
1&
0)
1*
#2750000000
0!
0&
#2755000000
1!
1#
0%
1&
1(
0*
#2760000000
0!
0&
#2765000000
1!
0#
1$
1&
0(
1)
#2770000000
0!
0&
#2775000000
1!
0$
1%
1&
0)
1*
#2780000000
0!
0&
#2785000000
1!
1#
0%
1&
1(
0*
#2790000000
0!
0&
#2795000000
1!
0#
1$
1&
0(
1)
#2800000000
0!
0&
#2805000000
1!
0$
1%
1&
0)
1*
#2810000000
0!
0&
#2815000000
1!
1#
0%
1&
1(
0*
#2820000000
0!
0&
#2825000000
1!
0#
1$
1&
0(
1)
#2830000000
0!
0&
#2835000000
1!
0$
1%
1&
0)
1*
#2840000000
0!
0&
#2845000000
1!
1#
0%
1&
1(
0*
#2850000000
0!
0&
#2855000000
1!
0#
1$
1&
0(
1)
#2860000000
0!
0&
#2865000000
1!
0$
1%
1&
0)
1*
#2870000000
0!
0&
#2875000000
1!
1#
0%
1&
1(
0*
#2880000000
0!
0&
#2885000000
1!
0#
1$
1&
0(
1)
#2890000000
0!
0&
#2895000000
1!
0$
1%
1&
0)
1*
#2900000000
0!
0&
#2905000000
1!
1#
0%
1&
1(
0*
#2910000000
0!
0&
#2915000000
1!
0#
1$
1&
0(
1)
#2920000000
0!
0&
#2925000000
1!
0$
1%
1&
0)
1*
#2930000000
0!
0&
#2935000000
1!
1#
0%
1&
1(
0*
#2940000000
0!
0&
#2945000000
1!
0#
1$
1&
0(
1)
#2950000000
0!
0&
#2955000000
1!
0$
1%
1&
0)
1*
#2960000000
0!
0&
#2965000000
1!
1#
0%
1&
1(
0*
#2970000000
0!
0&
#2975000000
1!
0#
1$
1&
0(
1)
#2980000000
0!
0&
#2985000000
1!
0$
1%
1&
0)
1*
#2990000000
0!
0&
#2995000000
1!
1#
0%
1&
1(
0*
#3000000000
0!
0&
#3005000000
1!
0#
1$
1&
0(
1)
#3010000000
0!
0&
#3015000000
1!
0$
1%
1&
0)
1*
#3020000000
0!
0&
#3025000000
1!
1#
0%
1&
1(
0*
#3030000000
0!
0&
#3035000000
1!
0#
1$
1&
0(
1)
#3040000000
0!
0&
#3045000000
1!
0$
1%
1&
0)
1*
#3050000000
0!
0&
#3055000000
1!
1#
0%
1&
1(
0*
#3060000000
0!
0&
#3065000000
1!
0#
1$
1&
0(
1)
#3070000000
0!
0&
#3075000000
1!
0$
1%
1&
0)
1*
#3080000000
0!
0&
#3085000000
1!
1#
0%
1&
1(
0*
#3090000000
0!
0&
#3095000000
1!
0#
1$
1&
0(
1)
#3100000000
0!
0&
#3105000000
1!
0$
1%
1&
0)
1*
#3110000000
0!
0&
#3115000000
1!
1#
0%
1&
1(
0*
#3120000000
0!
0&
#3125000000
1!
0#
1$
1&
0(
1)
#3130000000
0!
0&
#3135000000
1!
0$
1%
1&
0)
1*
#3140000000
0!
0&
#3145000000
1!
1#
0%
1&
1(
0*
#3150000000
0!
0&
#3155000000
1!
0#
1$
1&
0(
1)
#3160000000
0!
0&
#3165000000
1!
0$
1%
1&
0)
1*
#3170000000
0!
0&
#3175000000
1!
1#
0%
1&
1(
0*
#3180000000
0!
0&
#3185000000
1!
0#
1$
1&
0(
1)
#3190000000
0!
0&
#3195000000
1!
0$
1%
1&
0)
1*
#3200000000
0!
0&
#3205000000
1!
1#
0%
1&
1(
0*
#3210000000
0!
0&
#3215000000
1!
0#
1$
1&
0(
1)
#3220000000
0!
0&
#3225000000
1!
0$
1%
1&
0)
1*
#3230000000
0!
0&
#3235000000
1!
1#
0%
1&
1(
0*
#3240000000
0!
0&
#3245000000
1!
0#
1$
1&
0(
1)
#3250000000
0!
0&
#3255000000
1!
0$
1%
1&
0)
1*
#3260000000
0!
0&
#3265000000
1!
1#
0%
1&
1(
0*
#3270000000
0!
0&
#3275000000
1!
0#
1$
1&
0(
1)
#3280000000
0!
0&
#3285000000
1!
0$
1%
1&
0)
1*
#3290000000
0!
0&
#3295000000
1!
1#
0%
1&
1(
0*
#3300000000
0!
0&
#3305000000
1!
0#
1$
1&
0(
1)
#3310000000
0!
0&
#3315000000
1!
0$
1%
1&
0)
1*
#3320000000
0!
0&
#3325000000
1!
1#
0%
1&
1(
0*
#3330000000
0!
0&
#3335000000
1!
0#
1$
1&
0(
1)
#3340000000
0!
0&
#3345000000
1!
0$
1%
1&
0)
1*
#3350000000
0!
0&
#3355000000
1!
1#
0%
1&
1(
0*
#3360000000
0!
0&
#3365000000
1!
0#
1$
1&
0(
1)
#3370000000
0!
0&
#3375000000
1!
0$
1%
1&
0)
1*
#3380000000
0!
0&
#3385000000
1!
1#
0%
1&
1(
0*
#3390000000
0!
0&
#3395000000
1!
0#
1$
1&
0(
1)
#3400000000
0!
0&
#3405000000
1!
0$
1%
1&
0)
1*
#3410000000
0!
0&
#3415000000
1!
1#
0%
1&
1(
0*
#3420000000
0!
0&
#3425000000
1!
0#
1$
1&
0(
1)
#3430000000
0!
0&
#3435000000
1!
0$
1%
1&
0)
1*
#3440000000
0!
0&
#3445000000
1!
1#
0%
1&
1(
0*
#3450000000
0!
0&
#3455000000
1!
0#
1$
1&
0(
1)
#3460000000
0!
0&
#3465000000
1!
0$
1%
1&
0)
1*
#3470000000
0!
0&
#3475000000
1!
1#
0%
1&
1(
0*
#3480000000
0!
0&
#3485000000
1!
0#
1$
1&
0(
1)
#3490000000
0!
0&
#3495000000
1!
0$
1%
1&
0)
1*
#3500000000
0!
0&
#3505000000
1!
1#
0%
1&
1(
0*
#3510000000
0!
0&
#3515000000
1!
0#
1$
1&
0(
1)
#3520000000
0!
0&
#3525000000
1!
0$
1%
1&
0)
1*
#3530000000
0!
0&
#3535000000
1!
1#
0%
1&
1(
0*
#3540000000
0!
0&
#3545000000
1!
0#
1$
1&
0(
1)
#3550000000
0!
0&
#3555000000
1!
0$
1%
1&
0)
1*
#3560000000
0!
0&
#3565000000
1!
1#
0%
1&
1(
0*
#3570000000
0!
0&
#3575000000
1!
0#
1$
1&
0(
1)
#3580000000
0!
0&
#3585000000
1!
0$
1%
1&
0)
1*
#3590000000
0!
0&
#3595000000
1!
1#
0%
1&
1(
0*
#3600000000
0!
0&
#3605000000
1!
0#
1$
1&
0(
1)
#3610000000
0!
0&
#3615000000
1!
0$
1%
1&
0)
1*
#3620000000
0!
0&
#3625000000
1!
1#
0%
1&
1(
0*
#3630000000
0!
0&
#3635000000
1!
0#
1$
1&
0(
1)
#3640000000
0!
0&
#3645000000
1!
0$
1%
1&
0)
1*
#3650000000
0!
0&
#3655000000
1!
1#
0%
1&
1(
0*
#3660000000
0!
0&
#3665000000
1!
0#
1$
1&
0(
1)
#3670000000
0!
0&
#3675000000
1!
0$
1%
1&
0)
1*
#3680000000
0!
0&
#3685000000
1!
1#
0%
1&
1(
0*
#3690000000
0!
0&
#3695000000
1!
0#
1$
1&
0(
1)
#3700000000
0!
0&
#3705000000
1!
0$
1%
1&
0)
1*
#3710000000
0!
0&
#3715000000
1!
1#
0%
1&
1(
0*
#3720000000
0!
0&
#3725000000
1!
0#
1$
1&
0(
1)
#3730000000
0!
0&
#3735000000
1!
0$
1%
1&
0)
1*
#3740000000
0!
0&
#3745000000
1!
1#
0%
1&
1(
0*
#3750000000
0!
0&
#3755000000
1!
0#
1$
1&
0(
1)
#3760000000
0!
0&
#3765000000
1!
0$
1%
1&
0)
1*
#3770000000
0!
0&
#3775000000
1!
1#
0%
1&
1(
0*
#3780000000
0!
0&
#3785000000
1!
0#
1$
1&
0(
1)
#3790000000
0!
0&
#3795000000
1!
0$
1%
1&
0)
1*
#3800000000
0!
0&
#3805000000
1!
1#
0%
1&
1(
0*
